{
	"name": "Frostmourne",
	"baseManaCost": 6,
	"type": "WEAPON",
	"damage": 6,
	"durability": 2,
	"heroClass": "DEATH_KNIGHT",
	"rarity": "LEGENDARY",
	"description": "After this kills a minion, summon a 2/2 Scourge with its card text.",
	"trigger": {
		"eventTrigger": {
			"class": "AfterPhysicalAttackTrigger",
			"sourcePlayer": "SELF",
			"targetPlayer": "BOTH",
			"sourceEntityType": "HERO",
			"fireCondition": {
				"class": "IsDeadCondition"
			}
		},
		"spell": {
			"class": "SummonSpecialSpell",
			"target": "EVENT_TARGET",
			"attackBonus": 1,
			"hpBonus": 1,
			"name": "Scourge",
			"secondaryName": "UNDEAD"
		}
	},
	"collectible": true,
	"set": "CLASSIC",
	"fileFormatVersion": 1
}